{
  "id": "09_christianity",
  "name": {
    "en": "Christianity",
    "ru": "Христианство",
    "hu": "Kereszténység"
  },
  "questions": [
    {
      "word_hu": "felekezet",
      "example_hu": "Magyarország legjelentősebb felekezetei",
      "word_en": "denomination",
      "example_en": "Hungary’s most significant denominations",
      "word_ru": "конфессия",
      "example_ru": "Крупнейшие конфессии Венгрии"
    },
    {
      "word_hu": "Magyar Katolikus Egyház",
      "example_hu": "Magyar Katolikus Egyház",
      "word_en": "Hungarian Catholic Church",
      "example_en": "Hungarian Catholic Church",
      "word_ru": "Венгерская католическая церковь",
      "example_ru": "Венгерская католическая церковь"
    },
    {
      "word_hu": "Magyarországi Református Egyház",
      "example_hu": "Magyarországi Református Egyház",
      "word_en": "Reformed Church in Hungary",
      "example_en": "Reformed Church in Hungary",
      "word_ru": "Реформатская церковь в Венгрии",
      "example_ru": "Реформатская церковь в Венгрии"
    },
    {
      "word_hu": "Magyarországi Evangélikus Egyház",
      "example_hu": "Magyarországi Evangélikus Egyház",
      "word_en": "Evangelical Lutheran Church in Hungary",
      "example_en": "Evangelical Lutheran Church in Hungary",
      "word_ru": "Лютеранская церковь в Венгрии",
      "example_ru": "Лютеранская церковь в Венгрии"
    },
    {
      "word_hu": "Karácsony",
      "example_hu": "Karácsonykor Jézus születését ünneplik.",
      "word_en": "Christmas",
      "example_en": "At Christmas, Christians celebrate the birth of Jesus.",
      "word_ru": "Рождество",
      "example_ru": "На Рождество празднуют рождение Иисуса."
    },
    {
      "word_hu": "Húsvét",
      "example_hu": "Húsvétkor Jézus kereszthalálára emlékezünk.",
      "word_en": "Easter",
      "example_en": "At Easter, we remember Jesus’s crucifixion.",
      "word_ru": "Пасха",
      "example_ru": "На Пасху вспоминаем распятие Иисуса."
    },
    {
      "word_hu": "államalapítás napja",
      "example_hu": "Augusztus 20-a a magyar államalapítás napja.",
      "word_en": "Day of the founding of the state",
      "example_en": "20 August is the day of the founding of the Hungarian state.",
      "word_ru": "день основания государства",
      "example_ru": "20 августа — день основания венгерского государства."
    },
    {
      "word_hu": "Szent Jobb Körmenet",
      "example_hu": "A Szent Jobb Körmenetre kerül sor.",
      "word_en": "Procession of the Holy Right",
      "example_en": "There is a Procession of the Holy Right.",
      "word_ru": "Процессия Святой Десницы",
      "example_ru": "Проходит процессия Святой Десницы."
    },
    {
      "word_hu": "ereklye",
      "example_hu": "A király ereklyéjével.",
      "word_en": "relic",
      "example_en": "With the king’s relic.",
      "word_ru": "реликвия",
      "example_ru": "С реликвией короля."
    },
    {
      "word_hu": "tűzijáték",
      "example_hu": "Következik az esti tűzijáték.",
      "word_en": "fireworks",
      "example_en": "Then comes the evening fireworks.",
      "word_ru": "фейерверк",
      "example_ru": "Следует вечерний фейерверк."
    },
    {
      "word_hu": "szent",
      "example_hu": "Legfontosabb magyar szentek.",
      "word_en": "saint",
      "example_en": "Most important Hungarian saints.",
      "word_ru": "святой",
      "example_ru": "Важнейшие венгерские святые."
    },
    {
      "word_hu": "keresztény",
      "example_hu": "Az első keresztény magyar király.",
      "word_en": "Christian",
      "example_en": "The first Christian Hungarian king.",
      "word_ru": "христианский",
      "example_ru": "Первый христианский венгерский король."
    },
    {
      "word_hu": "vallás",
      "example_hu": "Római katolikus vallás",
      "word_en": "religion",
      "example_en": "Roman Catholic religion",
      "word_ru": "религия",
      "example_ru": "Римско-католическая религия"
    },
    {
      "word_hu": "Szent István",
      "example_hu": "I. Szent István király, az államalapító",
      "word_en": "Saint Stephen",
      "example_en": "King Saint Stephen, the founder of the state",
      "word_ru": "Szent István",
      "example_ru": "Король Szent István, основатель государства"
    },
    {
      "word_hu": "Szent László",
      "example_hu": "Szent László ... kiemelkedő uralkodó volt.",
      "word_en": "Saint Ladislaus",
      "example_en": "Saint Ladislaus was a prominent ruler.",
      "word_ru": "Szent László",
      "example_ru": "Szent László был выдающимся правителем."
    },
    {
      "word_hu": "egyházmegye",
      "example_hu": "Tíz egyházmegyét alapított.",
      "word_en": "diocese",
      "example_en": "He founded ten dioceses.",
      "word_ru": "епархия",
      "example_ru": "Он основал десять епархий."
    },
    {
      "word_hu": "püspökség",
      "example_hu": "Püspökségeket alapított.",
      "word_en": "bishopric",
      "example_en": "He founded bishoprics.",
      "word_ru": "епископия",
      "example_ru": "Он основал епископии."
    },
    {
      "word_hu": "érsekség",
      "example_hu": "Érsekségeket alapított.",
      "word_en": "archbishopric",
      "example_en": "He founded archbishoprics.",
      "word_ru": "архиепархия",
      "example_ru": "Он основал архиепархии."
    }
  ],
  "count": 18
}